direc
