Metadata-Version: 2.1
Name: up-test
Version: 0.0.4
Summary: first upload test
Home-page: http://www.csdn.net
Author: lyx
Author-email: Me@qq.com
License: LGPL
Platform: UNKNOWN
